[{"imports": ["smooth", "white"], "name": "spicy"}, {"imports": [], "name": "sheathing"}, {"imports": [], "name": "cobwebby"}, {"imports": ["broad", "scaly", "black", "tapering", "convex", "edible", "close", "fibrous", "free", "white", "woods", "red", "flat", "brown", "enlarging", "partial", "solitary", "bulbous", "smooth", "one", "pendant", "gray", "none", "pink", "several"], "name": "bruises"}, {"imports": ["scaly", "black", "tapering", "convex", "edible", "close", "fibrous", "foul", "no", "free", "white", "woods", "large", "buff", "grasses", "evanescent", "flat", "pink", "brown", "enlarging", "partial", "solitary", "yellow", "bulbous", "smooth", "scattered", "chocolate", "one", "pendant", "poisonous", "red", "silky", "gray", "none", "crowded", "several", "bruises"], "name": "broad"}, {"imports": ["broad", "black", "tapering", "convex", "edible", "close", "no", "free", "white", "narrow", "woods", "buff", "red", "flat", "pink", "brown", "enlarging", "partial", "evanescent", "solitary", "yellow", "bulbous", "smooth", "chocolate", "one", "pendant", "poisonous", "silky", "gray", "none", "foul", "missing", "several", "bruises"], "name": "scaly"}, {"imports": [], "name": "zone"}, {"imports": [], "name": "notched"}, {"imports": ["broad", "scaly", "black", "tapering", "edible", "buff", "close", "fibrous", "no", "free", "white", "narrow", "woods", "evanescent", "silky", "pink", "brown", "grasses", "enlarging", "partial", "solitary", "bulbous", "smooth", "chocolate", "one", "pendant", "poisonous", "gray", "none", "foul", "several", "bruises"], "name": "flat"}, {"imports": ["smooth", "white"], "name": "urban"}, {"imports": ["broad", "scaly", "black", "convex", "edible", "close", "fibrous", "no", "missing", "free", "white", "narrow", "woods", "red", "evanescent", "flat", "grasses", "pink", "brown", "partial", "solitary", "bulbous", "smooth", "one", "pendant", "poisonous", "silky", "buff", "gray", "none", "foul", "crowded", "several", "bruises"], "name": "tapering"}, {"imports": [], "name": "attached"}, {"imports": [], "name": "distant"}, {"imports": [], "name": "conical"}, {"imports": ["smooth", "white"], "name": "numerous"}, {"imports": ["broad", "scaly", "black", "tapering", "convex", "edible", "fibrous", "foul", "no", "paths", "free", "white", "narrow", "woods", "large", "buff", "red", "flat", "brown", "grasses", "enlarging", "evanescent", "solitary", "yellow", "bulbous", "smooth", "chocolate", "one", "pendant", "poisonous", "silky", "gray", "none", "pink", "missing", "several", "bruises", "partial"], "name": "close"}, {"imports": ["broad", "black", "tapering", "convex", "edible", "close", "fibrous", "no", "free", "white", "woods", "evanescent", "flat", "grasses", "pink", "brown", "enlarging", "partial", "solitary", "equal", "bulbous", "smooth", "scattered", "chocolate", "one", "pendant", "poisonous", "silky", "gray", "none", "foul", "crowded", "several", "bruises"], "name": "fibrous"}, {"imports": [], "name": "grooves"}, {"imports": ["smooth", "white"], "name": "almond"}, {"imports": [], "name": "green"}, {"imports": ["broad", "scaly", "black", "tapering", "convex", "edible", "buff", "close", "fibrous", "foul", "no", "paths", "missing", "free", "white", "narrow", "woods", "large", "grasses", "evanescent", "flat", "brown", "enlarging", "partial", "solitary", "bulbous", "smooth", "chocolate", "one", "pendant", "poisonous", "red", "silky", "gray", "none", "pink", "several", "bruises"], "name": "pink"}, {"imports": ["white", "partial", "smooth"], "name": "knobbed"}, {"imports": ["buff", "close", "no", "free", "white", "silky", "pink", "partial", "smooth", "one", "poisonous", "several"], "name": "paths"}, {"imports": ["broad", "scaly", "black", "tapering", "convex", "edible", "close", "fibrous", "foul", "no", "paths", "missing", "white", "narrow", "woods", "large", "buff", "evanescent", "flat", "equal", "brown", "grasses", "enlarging", "solitary", "yellow", "bulbous", "smooth", "scattered", "chocolate", "one", "pendant", "poisonous", "red", "silky", "gray", "none", "pink", "crowded", "several", "bruises", "partial"], "name": "free"}, {"imports": ["spicy", "broad", "scaly", "black", "urban", "tapering", "convex", "edible", "numerous", "close", "fibrous", "foul", "no", "paths", "missing", "free", "white", "narrow", "fishy", "woods", "meadows", "pungent", "large", "clustered", "buff", "anise", "evanescent", "flat", "knobbed", "equal", "brown", "two", "grasses", "enlarging", "solitary", "yellow", "bulbous", "smooth", "scattered", "leaves", "chocolate", "one", "pendant", "bell", "club", "poisonous", "red", "silky", "almond", "gray", "abundant", "none", "purple", "pink", "crowded", "several", "bruises", "partial"], "name": "white"}, {"imports": ["scaly", "tapering", "convex", "close", "no", "free", "white", "woods", "red", "evanescent", "flat", "brown", "partial", "smooth", "silky", "one", "poisonous", "buff", "pink", "missing", "several"], "name": "narrow"}, {"imports": [], "name": "cinnamon"}, {"imports": ["smooth", "white"], "name": "fishy"}, {"imports": ["broad", "scaly", "black", "flat", "tapering", "convex", "edible", "close", "fibrous", "no", "free", "white", "narrow", "red", "silky", "brown", "partial", "solitary", "bulbous", "smooth", "pink", "one", "pendant", "poisonous", "buff", "gray", "none", "several", "bruises"], "name": "woods"}, {"imports": ["white"], "name": "meadows"}, {"imports": ["white"], "name": "pungent"}, {"imports": [], "name": "rooted"}, {"imports": [], "name": "flaring"}, {"imports": ["pink", "brown", "broad", "enlarging", "partial", "close", "one", "bulbous", "no", "chocolate", "free", "white", "poisonous", "buff", "gray", "foul", "silky"], "name": "large"}, {"imports": ["white"], "name": "clustered"}, {"imports": [], "name": "cup"}, {"imports": ["broad", "scaly", "tapering", "edible", "close", "no", "free", "white", "narrow", "woods", "evanescent", "pink", "missing", "partial", "smooth", "silky", "one", "poisonous", "buff", "none", "several", "bruises"], "name": "red"}, {"imports": ["broad", "scaly", "flat", "tapering", "convex", "edible", "close", "fibrous", "no", "free", "white", "narrow", "missing", "silky", "pink", "brown", "red", "partial", "smooth", "one", "poisonous", "buff", "none", "crowded", "several"], "name": "evanescent"}, {"imports": [], "name": "sunken"}, {"imports": ["broad", "scaly", "tapering", "convex", "close", "fibrous", "no", "paths", "missing", "free", "white", "narrow", "woods", "large", "red", "evanescent", "flat", "foul", "brown", "grasses", "enlarging", "partial", "solitary", "yellow", "bulbous", "smooth", "chocolate", "one", "poisonous", "silky", "buff", "gray", "pink", "several"], "name": "silky"}, {"imports": [], "name": "rhizomorphs"}, {"imports": ["smooth", "white"], "name": "purple"}, {"imports": ["broad", "edible", "fibrous", "free", "white", "grasses", "brown", "partial", "smooth", "one", "pendant"], "name": "scattered"}, {"imports": [], "name": "universal"}, {"imports": ["broad", "black", "tapering", "convex", "edible", "close", "fibrous", "no", "free", "white", "flat", "pink", "brown", "partial", "smooth", "scattered", "chocolate", "one", "pendant", "enlarging", "silky", "gray", "none", "equal", "crowded"], "name": "grasses"}, {"imports": [], "name": "creosote"}, {"imports": ["broad", "scaly", "black", "tapering", "convex", "edible", "close", "fibrous", "foul", "no", "missing", "free", "white", "narrow", "woods", "large", "buff", "evanescent", "flat", "pink", "brown", "grasses", "enlarging", "solitary", "orange", "yellow", "bulbous", "smooth", "scattered", "chocolate", "one", "pendant", "poisonous", "silky", "gray", "none", "equal", "crowded", "several", "bruises", "partial"], "name": "brown"}, {"imports": ["broad", "scaly", "tapering", "convex", "edible", "close", "fibrous", "free", "white", "woods", "grasses", "flat", "equal", "brown", "enlarging", "bulbous", "smooth", "one", "pendant", "gray", "none", "pink", "bruises", "partial"], "name": "black"}, {"imports": ["smooth", "white"], "name": "two"}, {"imports": ["scaly", "tapering", "convex", "close", "no", "free", "white", "narrow", "red", "evanescent", "pink", "brown", "partial", "smooth", "one", "poisonous", "silky", "buff", "several"], "name": "missing"}, {"imports": ["broad", "scaly", "black", "convex", "edible", "close", "fibrous", "no", "free", "white", "large", "buff", "flat", "pink", "brown", "grasses", "solitary", "yellow", "bulbous", "smooth", "chocolate", "one", "pendant", "poisonous", "silky", "gray", "none", "foul", "several", "bruises", "partial"], "name": "enlarging"}, {"imports": ["broad", "scaly", "black", "tapering", "convex", "edible", "close", "fibrous", "foul", "no", "paths", "missing", "free", "white", "narrow", "woods", "large", "buff", "evanescent", "flat", "knobbed", "equal", "brown", "grasses", "enlarging", "solitary", "yellow", "bulbous", "smooth", "scattered", "leaves", "chocolate", "one", "pendant", "poisonous", "red", "silky", "gray", "none", "pink", "crowded", "several", "bruises"], "name": "partial"}, {"imports": ["broad", "scaly", "flat", "tapering", "convex", "edible", "close", "fibrous", "free", "white", "woods", "silky", "pink", "brown", "enlarging", "partial", "bulbous", "smooth", "chocolate", "one", "pendant", "gray", "none", "bruises"], "name": "solitary"}, {"imports": ["brown", "orange", "smooth"], "name": "orange"}, {"imports": ["broad", "scaly", "close", "no", "free", "white", "brown", "enlarging", "partial", "smooth", "chocolate", "one", "silky"], "name": "yellow"}, {"imports": ["broad", "scaly", "black", "flat", "tapering", "convex", "edible", "close", "fibrous", "no", "free", "white", "woods", "large", "silky", "brown", "enlarging", "partial", "solitary", "smooth", "pink", "chocolate", "one", "pendant", "poisonous", "buff", "gray", "none", "foul", "several", "bruises"], "name": "bulbous"}, {"imports": ["spicy", "broad", "scaly", "black", "urban", "tapering", "convex", "edible", "numerous", "close", "fibrous", "foul", "no", "paths", "missing", "free", "white", "narrow", "fishy", "woods", "buff", "anise", "evanescent", "flat", "knobbed", "equal", "brown", "two", "grasses", "enlarging", "solitary", "orange", "yellow", "bulbous", "smooth", "scattered", "leaves", "chocolate", "one", "pendant", "bell", "club", "poisonous", "red", "silky", "almond", "gray", "none", "purple", "pink", "crowded", "several", "bruises", "partial"], "name": "smooth"}, {"imports": [], "name": "descending"}, {"imports": ["partial", "one", "smooth", "no", "white"], "name": "leaves"}, {"imports": ["broad", "scaly", "flat", "convex", "close", "fibrous", "no", "free", "white", "large", "silky", "pink", "brown", "grasses", "enlarging", "partial", "solitary", "yellow", "bulbous", "smooth", "chocolate", "one", "poisonous", "buff", "gray", "foul", "several"], "name": "chocolate"}, {"imports": ["broad", "scaly", "black", "tapering", "convex", "edible", "close", "fibrous", "foul", "no", "paths", "missing", "free", "white", "narrow", "woods", "large", "buff", "evanescent", "flat", "equal", "brown", "grasses", "enlarging", "solitary", "yellow", "bulbous", "smooth", "scattered", "leaves", "chocolate", "pendant", "poisonous", "red", "silky", "gray", "none", "pink", "crowded", "several", "bruises", "partial"], "name": "one"}, {"imports": ["broad", "scaly", "black", "tapering", "convex", "edible", "close", "fibrous", "free", "white", "woods", "flat", "brown", "grasses", "enlarging", "solitary", "bulbous", "smooth", "scattered", "one", "poisonous", "gray", "none", "pink", "several", "bruises", "partial"], "name": "pendant"}, {"imports": ["white", "smooth"], "name": "bell"}, {"imports": ["smooth", "white"], "name": "club"}, {"imports": ["broad", "scaly", "tapering", "convex", "close", "fibrous", "paths", "free", "white", "narrow", "woods", "large", "red", "evanescent", "flat", "pink", "brown", "missing", "enlarging", "partial", "bulbous", "smooth", "chocolate", "one", "pendant", "silky", "buff", "gray", "foul", "several", "no"], "name": "poisonous"}, {"imports": ["broad", "scaly", "black", "tapering", "edible", "close", "fibrous", "foul", "no", "missing", "free", "white", "narrow", "woods", "buff", "evanescent", "silky", "brown", "grasses", "enlarging", "partial", "solitary", "bulbous", "smooth", "chocolate", "one", "pendant", "poisonous", "gray", "none", "pink", "several", "bruises"], "name": "convex"}, {"imports": ["broad", "scaly", "tapering", "convex", "close", "no", "paths", "free", "white", "narrow", "woods", "large", "red", "evanescent", "flat", "foul", "brown", "missing", "enlarging", "partial", "bulbous", "smooth", "chocolate", "one", "poisonous", "silky", "pink", "several"], "name": "buff"}, {"imports": ["broad", "scaly", "black", "tapering", "convex", "edible", "close", "fibrous", "foul", "no", "free", "white", "woods", "large", "flat", "brown", "grasses", "enlarging", "partial", "solitary", "bulbous", "smooth", "chocolate", "one", "pendant", "poisonous", "silky", "gray", "none", "pink", "several", "bruises"], "name": "gray"}, {"imports": ["white"], "name": "abundant"}, {"imports": ["broad", "scaly", "black", "tapering", "convex", "close", "fibrous", "no", "free", "white", "woods", "grasses", "evanescent", "flat", "pink", "brown", "enlarging", "partial", "solitary", "bulbous", "smooth", "scattered", "one", "pendant", "red", "gray", "none", "equal", "crowded", "several", "bruises"], "name": "edible"}, {"imports": ["broad", "scaly", "black", "tapering", "convex", "edible", "close", "fibrous", "no", "free", "white", "woods", "red", "evanescent", "flat", "grasses", "equal", "brown", "enlarging", "partial", "solitary", "bulbous", "smooth", "one", "pendant", "gray", "pink", "crowded", "several", "bruises"], "name": "none"}, {"imports": ["brown", "fibrous", "black", "edible", "partial", "one", "smooth", "free", "white", "none", "grasses", "no"], "name": "equal"}, {"imports": ["brown", "broad", "scaly", "flat", "tapering", "enlarging", "convex", "partial", "close", "fibrous", "one", "bulbous", "smooth", "no", "chocolate", "free", "white", "several", "poisonous", "buff", "gray", "large", "pink", "silky"], "name": "foul"}, {"imports": ["broad", "tapering", "edible", "fibrous", "no", "free", "white", "evanescent", "brown", "grasses", "partial", "smooth", "one", "none"], "name": "crowded"}, {"imports": [], "name": "musty"}, {"imports": ["broad", "scaly", "flat", "tapering", "convex", "edible", "close", "fibrous", "no", "paths", "missing", "free", "white", "narrow", "woods", "red", "evanescent", "silky", "pink", "brown", "enlarging", "partial", "bulbous", "smooth", "chocolate", "one", "pendant", "poisonous", "buff", "gray", "none", "foul", "bruises"], "name": "several"}, {"imports": ["broad", "scaly", "tapering", "convex", "edible", "close", "fibrous", "paths", "missing", "free", "white", "narrow", "woods", "large", "grasses", "evanescent", "flat", "pink", "brown", "red", "enlarging", "partial", "equal", "yellow", "bulbous", "smooth", "leaves", "chocolate", "one", "poisonous", "silky", "buff", "gray", "none", "foul", "crowded", "several"], "name": "no"}, {"imports": ["smooth", "white"], "name": "anise"}, {"imports": [], "name": "waste"}]